{
  "UniqueID": "lab_coat_001",
  "Name": "Basic Lab Coat",
  "Type": "wearable",
  "Description": "A standard white lab coat, useful for scientific work.",
  "Picture": "Assets/images/objects/lab_coat.png",
  "Owner": "duffelbag_001",
  "AlwaysPresent": false,
  "PresentOnFirstVisit": false,
  "CanExamine": true,
  "CanPickUp": true,
  "CanDrop": true,
  "CanCombine": false,
  "CanSpawn": false,
  "Price": 0,
  "Bonuses": {
    "Defence": 2
  },
  "Tooltip": "Examine, Take, Drop, Equip, Unequip",
  "ActionsMenu": [
    {
      "Action": "Examine",
      "Description": "Look at the Lab Coat closely."
    },
    {
      "Action": "Take",
      "Description": "Pick up the Lab Coat."
    },
    {
      "Action": "Drop",
      "Description": "Drop the Lab Coat."
    },
    {
      "Action": "Equip",
      "Description": "Wear the Lab Coat."
    },
    {
      "Action": "Unequip",
      "Description": "Remove the Lab Coat."
    }
  ],
  "CustomActions": [],
  "CombinableWith": [],
  "CreatesOnCombine": "",
  "CustomProperties": [
    {
      "Property": "Equipped",
      "Value": true
    }
  ]
}
